pwm_servo_driver/IO_Types.py
pwm_servo_driver/Servo.py
pwm_servo_driver/__init__.py
pwm_servo_driver-0.1.0.dist-info/METADATA
pwm_servo_driver-0.1.0.dist-info/WHEEL
pwm_servo_driver-0.1.0.dist-info/licenses/LICENSE
pwm_servo_driver-0.1.0.dist-info/RECORD
