Metadata-Version: 2.3
Name: pwm_servo_driver
Version: 0.1.0
Summary: Python interface for PWM servo driver
Project-URL: Homepage, https://github.com/T-N-S/pwm_servo_driver
Author-email: Tim Schumann <gerb008701@gmail.com>
License-File: LICENSE
